pobaidu/__init__.py
pobaidu/api/__init__.py
pobaidu/api/face.py
pobaidu/api/imageprocess.py
pobaidu/core/Face.py
pobaidu/core/ImageProcess.py
pobaidu/core/__init__.py
pobaidu/lib/CommonUtils.py
pobaidu/lib/Config.py
pobaidu/lib/Const.py
pobaidu/lib/FileUtils.py
pobaidu/lib/__init__.py
tests/__init__.py
tests/test_ai.py
pobaidu-0.0.4.dist-info/LICENSE
pobaidu-0.0.4.dist-info/METADATA
pobaidu-0.0.4.dist-info/WHEEL
pobaidu-0.0.4.dist-info/top_level.txt
pobaidu-0.0.4.dist-info/RECORD
