Metadata-Version: 2.1
Name: pobaidu
Version: 0.0.4
Summary: pip install pobaidu
Home-page: http://python-office.com/
Author: CoderWanFeng
Author-email: 1957875073@qq.com
License: MIT
Project-URL: Bug Tracker, https://github.com/CoderWanFeng/pobaidu/issues
Project-URL: Documentation, https://github.com/CoderWanFeng/pobaidu/blob/main/README.md
Project-URL: Source Code, https://github.com/CoderWanFeng/pobaidu
Platform: any
Requires-Python: >=3.7
License-File: LICENSE
Requires-Dist: baidu-aip
Requires-Dist: toml
Requires-Dist: charset-normalizer
Requires-Dist: chardet
